.coveragerc
.dockerignore
.editorconfig
.travis-devel-requirements.txt
.travis-lowest-requirements.txt
.travis-release-requirements.txt
.travis.invenio.cfg
AUTHORS.rst
CHANGES.rst
LICENSE
MANIFEST.in
README.rst
RELEASE-NOTES.rst
babel.ini
pytest.ini
requirements-devel.txt
requirements-docs.txt
requirements.py
run-tests.sh
setup.cfg
setup.py
docs/Makefile
docs/conf.py
docs/index.rst
docs/make.bat
docs/_ext/ultramock.py
invenio_grobid/__init__.py
invenio_grobid/api.py
invenio_grobid/bundles.py
invenio_grobid/config.py
invenio_grobid/errors.py
invenio_grobid/ext.py
invenio_grobid/mapping.py
invenio_grobid/version.py
invenio_grobid/views.py
invenio_grobid.egg-info/PKG-INFO
invenio_grobid.egg-info/SOURCES.txt
invenio_grobid.egg-info/dependency_links.txt
invenio_grobid.egg-info/entry_points.txt
invenio_grobid.egg-info/not-zip-safe
invenio_grobid.egg-info/requires.txt
invenio_grobid.egg-info/top_level.txt
invenio_grobid/static/css/grobid/grobid.css
invenio_grobid/static/js/grobid/grobid.js
invenio_grobid/static/js/grobid/init.js
invenio_grobid/static/js/grobid/templates/error.mustache
invenio_grobid/static/js/grobid/templates/result.mustache
invenio_grobid/static/js/grobid/templates/success.mustache
invenio_grobid/static/js/grobid/templates/waiting.mustache
invenio_grobid/templates/grobid/base.html
invenio_grobid/templates/grobid/index.html
misc/header.py
misc/header.rst
tests/__init__.py
tests/conftest.py
tests/test_api.py
tests/test_mapping.py
tests/fixtures/article.pdf
tests/fixtures/article.xml
tests/fixtures/garbage.pdf