Metadata-Version: 1.1
Name: invenio-grobid
Version: 0.2.0
Summary: Invenio module to interact with Grobid API for metadata extraction.
Home-page: https://github.com/inspirehep/invenio-grobid
Author: CERN
Author-email: feedback@inspirehep.net
License: GPLv2
Keywords: invenio
Platform: any
Classifier: Environment :: Web Environment
Classifier: Intended Audience :: Developers
Classifier: License :: OSI Approved :: GNU General Public License v2 (GPLv2)
Classifier: Operating System :: OS Independent
Classifier: Programming Language :: Python
Classifier: Topic :: Internet :: WWW/HTTP :: Dynamic Content
Classifier: Topic :: Software Development :: Libraries :: Python Modules
Classifier: Programming Language :: Python :: 2
Classifier: Programming Language :: Python :: 2.7
Classifier: Development Status :: 1 - Planning
